[
    {
      "title": "Lumostudy",
      "tags": ["Java", "Angular", "Spring", "PostgreSQL", "Typescript"],
      "info": "Aplicativo para o gerenciamento de estudos (em desenvolvimento)",
      "repoLink": "https://github.com/Beforg/Lumostudy" 
    },
    {
      "title": "AtendimentosApp",
      "tags": ["JavaFX", "PostgreSQL", "CSS"],
      "info": "Sistema para o atendimento e fechamento de caixa de uma empresa de embalagens",
      "repoLink": "https://github.com/Beforg/AtendimentosAPP" 
    },
    {
      "title": "Controle de Estoque",
      "tags": ["C#","SQL Server 2019"],
      "info": "Sistema para controle do almoxarifado de uma empresa de Construções, auxiliando na entrada e saída de materiais",
      "repoLink": "https://github.com/Beforg/Controle-De-Estoque" 
    },
    {
      "title": "Task+",
      "tags": ["Java", "Spring", "HTML", "CSS", "PostgreSQL"],
      "info": "Projeto de gerenciamento de tarefas com uma API Restful feita em Java",
      "repoLink": "https://github.com/Beforg/Task-Plus" 
    },
    {
      "title": "LifeSync",
      "tags": ["JavaFX", "Spring", "CSS"],
      "info": "Aplicativo Desktop de organização pessoal feita em java",
      "repoLink": "https://github.com/Beforg/LifeSync" 
    }
    
  ]